canbro/__init__.py
canbro/e2e.py
canbro/message.py
canbro/network.py
canbro/node.py
canbro-0.1.1.dist-info/METADATA
canbro-0.1.1.dist-info/WHEEL
canbro-0.1.1.dist-info/entry_points.txt
canbro-0.1.1.dist-info/licenses/LICENSE
canbro-0.1.1.dist-info/RECORD
