Metadata-Version: 2.4
Name: canbro
Version: 0.1.1
Summary: This package extend the python-can with the broqer package. This provides the functionality to work in a reactive style with can signals and messages.
Project-URL: Homepage, https://github.com/lki1354/python-canbro
Project-URL: Documentation, https://readthedocs.org
Project-URL: Repository, https://github.com/lki1354/python-canbro.git
Project-URL: Bug Tracker, https://github.com/lki1354/python-canbro/issues
Author-email: Lukas Riegler <lukasantonriegler@gmail.com>
Maintainer-email: Lukas Riegler <lukasantonriegler@gmail.com>
License:                    GNU LESSER GENERAL PUBLIC LICENSE
License-File: LICENSE
Keywords: ARXML,DBC,can,reactive
Classifier: Development Status :: 2 - Pre-Alpha
Classifier: Intended Audience :: Developers
Classifier: License :: OSI Approved :: MIT License
Classifier: Programming Language :: Python :: 3.10
Classifier: Programming Language :: Python :: 3.11
Classifier: Programming Language :: Python :: 3.12
Requires-Python: >=3.10
Requires-Dist: broqer>=3.0.3
Requires-Dist: cantools>=39.4.4
Requires-Dist: python-can>=4.3.1
